micropython_uplot/__init__.py
micropython_uplot/bar.py
micropython_uplot/cartesian.py
micropython_uplot/colors.py
micropython_uplot/fillbetween.py
micropython_uplot/logging.py
micropython_uplot/map.py
micropython_uplot/plot.py
micropython_uplot/scatter.py
micropython_uplot/utils.py
micropython_uplot-0.5.0.dist-info/LICENSE
micropython_uplot-0.5.0.dist-info/METADATA
micropython_uplot-0.5.0.dist-info/WHEEL
micropython_uplot-0.5.0.dist-info/top_level.txt
micropython_uplot-0.5.0.dist-info/RECORD
